chat_summary/__init__.py
chat_summary/chat.py
chat_summary/chat_summary.py
chat_summary/game.py
chat_summary/games.py
chat_summary/get_available_games.py
chat_summary/messages.py
chat_summary/send_message.py
chat_summary-1.1.0.dist-info/LICENSE
chat_summary-1.1.0.dist-info/METADATA
chat_summary-1.1.0.dist-info/WHEEL
chat_summary-1.1.0.dist-info/entry_points.txt
chat_summary-1.1.0.dist-info/top_level.txt
chat_summary-1.1.0.dist-info/RECORD
