Metadata-Version: 2.1
Name: chat-summary
Version: 1.1.0
Summary: A tool to get an iMessage group chat summary for popular internet games.
Home-page: https://github.com/samirg1/chat-summary
Author: Samir Gupta
Author-email: srgupta@bigpond.com
License: MIT
Keywords: summary,wordle,nerdle,connections,chat,imessage
Classifier: License :: OSI Approved :: MIT License
Classifier: Programming Language :: Python :: 3
Classifier: Programming Language :: Python :: 3 :: Only
Classifier: Programming Language :: Python :: 3.10
Classifier: Programming Language :: Python :: 3.11
Classifier: Programming Language :: Python :: Implementation :: CPython
Requires-Python: >=3.10.0
License-File: LICENSE
Requires-Dist: pandas >=1.5.1
